{"stats":{"minecraft:used":{"endgate_armor:endgate_helmet":1,"endgate_armor:endgate_leggings":1,"endgate_armor:endgate_boots":1,"endgate_armor:endgate_chestplate":1},"minecraft:dropped":{"endgate_armor:endgate_helmet":1},"minecraft:custom":{"minecraft:time_since_rest":3516,"minecraft:leave_game":8,"minecraft:play_time":3516,"minecraft:time_since_death":3516,"minecraft:walk_one_cm":1182,"minecraft:total_world_time":3754,"minecraft:drop":1},"minecraft:picked_up":{"endgate_armor:endgate_helmet":1}},"DataVersion":3465}